{"cameraMode":{"drawMode":0,"name":"Shaded","section":"Shading Mode"},"sceneLighting":true,"audioPlay":false,"sceneViewState":{"m_AlwaysRefresh":false,"showFog":true,"showSkybox":true,"showFlares":true,"showImageEffects":true,"showParticleSystems":true,"showVisualEffectGraphs":true,"m_FxEnabled":true},"in2DMode":false,"pivot":{"x":130.06802368164063,"y":164.49465942382813,"z":202.0426025390625},"rotation":{"x":0.19315768778324128,"y":0.3710205852985382,"z":-0.07919058948755264,"w":0.9048470854759216},"size":12.12435531616211,"orthographic":false}